topology_connect/__init__.py
topology_connect/node.py
topology_connect/platform.py
topology_connect/shell.py
topology_connect/nodes/__init__.py
topology_connect/nodes/host.py
topology_connect-1.0.0.dist-info/LICENSE
topology_connect-1.0.0.dist-info/METADATA
topology_connect-1.0.0.dist-info/WHEEL
topology_connect-1.0.0.dist-info/entry_points.txt
topology_connect-1.0.0.dist-info/top_level.txt
topology_connect-1.0.0.dist-info/RECORD
