Metadata-Version: 2.1
Name: topology-connect
Version: 1.0.0
Summary: SSH/Telnet/etc connection Platform Engine plugin for the Network Topology Framework.
Home-page: http://topology-connect.rtfd.org/
Author: Hewlett Packard Enterprise Development LP
Author-email: hpe-networking@lists.hp.com
License: UNKNOWN
Keywords: topology_connect
Platform: UNKNOWN
Classifier: Development Status :: 3 - Alpha
Classifier: Intended Audience :: Developers
Classifier: License :: OSI Approved :: Apache Software License
Classifier: Natural Language :: English
Classifier: Operating System :: POSIX :: Linux
Classifier: Programming Language :: Python :: 2
Classifier: Programming Language :: Python :: 2.7
Classifier: Programming Language :: Python :: 3
Classifier: Programming Language :: Python :: 3.4
Requires-Dist: six
Requires-Dist: pexpect
Requires-Dist: topology (>=1.8.0)
